{
  "id": "10346",
  "title": "Can we stabilize an inverted pendulum with feedback from a time-of-flight camera?",
  "authors": [],
  "year": "2026",
  "venue": "2026",
  "venue_full": "2026",
  "doi": "",
  "arxiv_id": "",
  "IF": null,
  "quartile": null,
  "type": "other",
  "tags": [
    "Proof-of-Concept",
    "Paper #10346",
    "2026",
    "Inverted Pendulum",
    "ToF Camera",
    "State Estimation",
    "Feedback Control",
    "LQG Regulator"
  ],
  "keywords": [],
  "scholar": "files",
  "tldr": "",
  "pdf_name": "Czubarow et al. - 2026 - Can we stabilize an inverted pendulum with feedback from a time-of-flight camera.pdf",
  "related_papers": [
    "10342",
    "10343",
    "10344",
    "10345",
    "10347",
    "10348"
  ],
  "related_by_scholar": true
}