{
  "id": "10491",
  "title": "Adaptive prescribed-time formation control for nonholonomic vehicles subject to uncertain disturbances",
  "authors": [],
  "year": "2025",
  "venue": "IEEE Transactions (2025)",
  "venue_full": "IEEE Transactions (2025)",
  "doi": "",
  "arxiv_id": "",
  "IF": null,
  "quartile": null,
  "type": "other",
  "tags": [
    "预设时间控制",
    "自适应抗扰",
    "编队控制",
    "Paper 10491",
    "非完整约束",
    "2025",
    "Xiangke Wang"
  ],
  "keywords": [
    "formation control"
  ],
  "scholar": "files",
  "tldr": "",
  "pdf_name": "Zhao et al. - 2025 - Adaptive prescribed-time formation control for nonholonomic vehicles subject to uncertain disturbanc.pdf",
  "related_papers": [
    "10453",
    "10464",
    "10472",
    "10473",
    "10474",
    "10484",
    "10485",
    "10486",
    "10487",
    "10488",
    "10489",
    "10490",
    "10493",
    "10494",
    "10495",
    "10496",
    "10497"
  ],
  "related_by_scholar": true
}